{
  "_fv": 24,
  "_type": "armor",
  "definition": {
    "enableHelmet": false,
    "textureHelmet": "",
    "enableBody": true,
    "textureBody": "tianshayupao",
    "enableLeggings": false,
    "textureLeggings": "",
    "enableBoots": false,
    "textureBoots": "",
    "onBodyTick": {
      "name": "Tianshayupao2XiongJiaShiJianMeiYouXiKe"
    },
    "creativeTab": {
      "value": "CUSTOM:Zaomengxiyou"
    },
    "armorTextureFile": "tianshayupao_",
    "helmetName": "Tianshayupao 2 头盔",
    "bodyName": "Tianshayupao 2 胸甲",
    "leggingsName": "Tianshayupao 2 护腿",
    "bootsName": "Tianshayupao 2 靴子",
    "helmetSpecialInfo": [],
    "bodySpecialInfo": [
      "§3传说由鲲鹏羽毛编织成的法袍，藏有无限的法力，穿上后腾云驾雾，翱翔云端。（真的可以飞，更加持久）"
    ],
    "leggingsSpecialInfo": [],
    "bootsSpecialInfo": [],
    "helmetModelName": "Default",
    "helmetModelPart": "Helmet",
    "helmetModelTexture": "From armor",
    "bodyModelName": "Default",
    "bodyModelPart": "Body",
    "armsModelPartL": "Arms L",
    "armsModelPartR": "Arms R",
    "bodyModelTexture": "From armor",
    "leggingsModelName": "Default",
    "leggingsModelPartL": "Leggings L",
    "leggingsModelPartR": "Leggings R",
    "leggingsModelTexture": "From armor",
    "bootsModelName": "Default",
    "bootsModelPartL": "Boots L",
    "bootsModelPartR": "Boots R",
    "bootsModelTexture": "From armor",
    "helmetImmuneToFire": false,
    "bodyImmuneToFire": false,
    "leggingsImmuneToFire": false,
    "bootsImmuneToFire": false,
    "maxDamage": 0,
    "damageValueHelmet": 2,
    "damageValueBody": 16,
    "damageValueLeggings": 5,
    "damageValueBoots": 2,
    "enchantability": 30,
    "toughness": 1.7,
    "knockbackResistance": 0.0,
    "equipSound": {
      "value": ""
    },
    "repairItems": []
  }
}