{
  "type": "minecraft:entity",
  "pools": [
    {
      "rolls": {
        "min": 0,
        "max": 1
      },
      "entries": [
        {
          "type": "minecraft:item",
          "name": "zaomengxiyou:wangchuanriverworld",
          "weight": 1,
          "functions": [
            {
              "function": "set_count",
              "count": {
                "min": 1,
                "max": 1
              }
            }
          ]
        }
      ]
    },
    {
      "rolls": {
        "min": 0,
        "max": 1
      },
      "entries": [
        {
          "type": "minecraft:item",
          "name": "zaomengxiyou:wangchuanportal",
          "weight": 1,
          "functions": [
            {
              "function": "set_count",
              "count": {
                "min": 0,
                "max": 10
              }
            }
          ]
        }
      ]
    },
    {
      "rolls": 1,
      "bonus_rolls": 1,
      "entries": [
        {
          "type": "minecraft:item",
          "name": "zaomengxiyou:ghostkingsword",
          "weight": 2,
          "functions": [
            {
              "function": "set_count",
              "count": {
                "min": 1,
                "max": 1
              }
            },
            {
              "function": "minecraft:apply_bonus",
              "enchantment": "minecraft:fortune",
              "formula": "minecraft:ore_drops"
            }
          ]
        },
        {
          "type": "minecraft:item",
          "name": "zaomengxiyou:jyyslv_1",
          "weight": 3,
          "functions": [
            {
              "function": "set_count",
              "count": {
                "min": 1,
                "max": 10
              }
            }
          ]
        },
        {
          "type": "minecraft:item",
          "name": "zaomengxiyou:huoluobo",
          "weight": 3,
          "functions": [
            {
              "function": "set_count",
              "count": {
                "min": 1,
                "max": 5
              }
            }
          ]
        },
        {
          "type": "minecraft:item",
          "name": "zaomengxiyou:yujingping",
          "weight": 3,
          "functions": [
            {
              "function": "set_count",
              "count": {
                "min": 1,
                "max": 5
              }
            }
          ]
        }
      ]
    }
  ]
}